pycellbase/__init__.py
pycellbase/cbclient.py
pycellbase/cbconfig.py
pycellbase/cbrestclients.py
pycellbase/commons.py
pycellbase-7.0.0.data/scripts/cbtools.py
pycellbase-7.0.0.dist-info/licenses/LICENSE.txt
pycellbase-7.0.0.dist-info/METADATA
pycellbase-7.0.0.dist-info/WHEEL
pycellbase-7.0.0.dist-info/top_level.txt
pycellbase-7.0.0.dist-info/RECORD
