Metadata-Version: 2.4
Name: pycellbase
Version: 7.0.0
Summary: Python client for CellBase
Home-page: https://github.com/opencb/cellbase/tree/develop/clients/python
Author: Daniel Perez-Gil
Author-email: dperezgil89@gmail.com
License: Apache Software License
Project-URL: Documentation, http://docs.opencb.org/display/cellbase/RESTful+Web+Services
Project-URL: Tutorial, http://docs.opencb.org/display/cellbase/Python+client+library
Project-URL: Source, https://github.com/opencb/cellbase/tree/develop/clients/python
Project-URL: CellBase, https://github.com/opencb/cellbase
Project-URL: CellBase Documentation, http://docs.opencb.org/display/cellbase/CellBase+Home
Project-URL: Bug Reports, https://github.com/opencb/cellbase/issues
Keywords: opencb cellbase bioinformatics database
Classifier: Development Status :: 5 - Production/Stable
Classifier: Intended Audience :: Developers
Classifier: Topic :: Scientific/Engineering :: Bio-Informatics
Classifier: License :: OSI Approved :: Apache Software License
Classifier: Programming Language :: Python :: 2.7
Classifier: Programming Language :: Python :: 3
Classifier: Programming Language :: Python :: 3.5
License-File: LICENSE.txt
Requires-Dist: requests
Requires-Dist: pyyaml
Requires-Dist: retrying
Dynamic: author
Dynamic: author-email
Dynamic: classifier
Dynamic: description
Dynamic: description-content-type
Dynamic: home-page
Dynamic: keywords
Dynamic: license
Dynamic: license-file
Dynamic: project-url
Dynamic: requires-dist
Dynamic: summary
